sam_handler/__init__.py
sam_handler/handler.py
sceptre_sam_handler-1.0.0.dist-info/LICENSE
sceptre_sam_handler-1.0.0.dist-info/METADATA
sceptre_sam_handler-1.0.0.dist-info/WHEEL
sceptre_sam_handler-1.0.0.dist-info/entry_points.txt
sceptre_sam_handler-1.0.0.dist-info/top_level.txt
sceptre_sam_handler-1.0.0.dist-info/RECORD
