Metadata-Version: 2.1
Name: sceptre-sam-handler
Version: 1.0.0
Summary: Packages and renders SAM templates for use
Home-page: https://github.com/sceptre/sceptre-sam-handler
Author: Jon Falkenstein
License: Apache2
Keywords: sceptre,sceptre-template-handler,sam,aws,cloudformation
Classifier: Intended Audience :: Developers
Classifier: Natural Language :: English
Classifier: Environment :: Console
Classifier: Programming Language :: Python :: 3.7
Classifier: Programming Language :: Python :: 3.8
Classifier: Programming Language :: Python :: 3.9
Classifier: Programming Language :: Python :: 3.10
Requires-Python: >=3.6
License-File: LICENSE
Requires-Dist: sceptre (>=4.0)
Provides-Extra: sam
Requires-Dist: aws-sam-cli ; extra == 'sam'
Provides-Extra: test
Requires-Dist: pytest (>=3.2.0) ; extra == 'test'
Requires-Dist: pyfakefs (>=4.5.0) ; extra == 'test'
